zx_agents/__init__.py
zx_agents/model_provider.py
zx_agents/stream_processor.py
zx_agents-0.1.1.dist-info/METADATA
zx_agents-0.1.1.dist-info/WHEEL
zx_agents-0.1.1.dist-info/top_level.txt
zx_agents-0.1.1.dist-info/RECORD
