Metadata-Version: 2.4
Name: zx_agents
Version: 0.1.1
Summary: OpenAI agents customize package
Author-email: MENG <meng@zxtech.info>
Classifier: Programming Language :: Python :: 3
Classifier: License :: OSI Approved :: MIT License
Classifier: Operating System :: OS Independent
Requires-Python: >=3.12.2
